{
  "companyName": "Notion",
  "synthesis": {
    "summaries": {
      "tldr": "Notion faces significant usability friction, with users expressing frustration over app stability, customization, and feature integration.",
      "highlights": [
        "Usability friction is the primary concern, with multiple areas like app stability and text formatting causing issues.",
        "Customization requests are prevalent, with users wanting more control over the interface aesthetics.",
        "Notion Mail and task management features are notably problematic, leading to user dissatisfaction.",
        "Users are experiencing significant frustration with the app's performance and stability.",
        "Despite issues, users still express a desire for enhanced features and integrations."
      ],
      "executiveBrief": "The analysis of 50 user feedback entries reveals that Notion is currently facing considerable usability friction, particularly in areas such as app stability, customization options, and feature integration. Users have reported frequent crashes, difficulties with the text formatting menu, and dissatisfaction with Notion Mail's functionality. Customization requests are also prominent, with users seeking more control over the interface's appearance. Despite these challenges, there is a clear demand for enhanced features and integrations, indicating a strong user interest in the platform's potential. Addressing these usability issues and expanding customization options could significantly improve user satisfaction and retention."
    },
    "sentiment": {
      "positive": 4,
      "neutral": 20,
      "negative": 26,
      "mood": "Concerning",
      "moodExplanation": "The sentiment analysis indicates a concerning mood, with a majority of feedback being negative or highlighting usability issues, suggesting significant user dissatisfaction."
    },
    "focusAreas": [
      {
        "id": "1",
        "title": "AI Assistance",
        "category": "usability_friction",
        "items": [
          {
            "type": "Constructive",
            "category": "Support Question",
            "problemMetadata": {
              "rootCause": "Certainty",
              "featureArea": "AI Assistance",
              "impactType": "Retention",
              "urgencySignal": "High",
              "prioritization": {
                "impactScore": 7,
                "urgencyScore": 8,
                "effortEstimate": 2
              }
            },
            "delightMetadata": null,
            "summary": {
              "actionableInsight": "Investigate clarifying the limitations of AI assistance for free users to enhance user understanding and retention.",
              "replyDraft": "Hi there! Thanks for your question about AI help in Notion. While the AI can assist you in many ways, there are some limitations based on your plan. We recommend checking our documentation for detailed information on what you can do with the free version. Happy Notioning!",
              "keyQuote": "Is the AI help unlimited?"
            },
            "confidence": 0.85,
            "reasoning": "The feedback expresses a clear question about the limitations of AI assistance, indicating a need for clarity and support. This falls under 'Support Question' as the user seeks information to better utilize the product.",
            "sourceUrl": "https://www.reddit.com/r/Notion/comments/1uban65/ai_help_in_the_pages_databases_etc/",
            "sourceId": "1uban65",
            "originalTitle": "AI help in the pages, databases, etc.",
            "signalScore": 0.5999999999999999,
            "impactData": {
              "score": 2.1,
              "maxScore": 10,
              "breakdown": {
                "reach": {
                  "value": 0,
                  "weight": 0.4
                },
                "sentiment": {
                  "value": 7,
                  "weight": 0.3
                },
                "velocity": {
                  "value": 0,
                  "weight": 0.3
                }
              },
              "rationale": "Score based on standard engagement metrics.",
              "stakes": {
                "type": "risk",
                "message": "Risk if ignored: Continued user frustration, possible support ticket increase."
              }
            }
          }
        ],
        "totalScore": 2.1,
        "quotes": [
          "Is the AI help unlimited?"
        ],
        "segments": {},
        "frequency": 1,
        "avgImpact": 2.1,
        "topQuote": "Is the AI help unlimited?",
        "affectedSegments": [],
        "stakes": {
          "type": "risk",
          "message": "Risk if ignored: Continued user frustration, possible support ticket increase."
        },
        "scoreRationale": "Score based on standard engagement metrics.",
        "severityLabel": "Medium",
        "rootCause": "Unclear AI capabilities and limitations.",
        "impactScore": 2.1,
        "trend": "new",
        "trendDelta": 0
      },
      {
        "id": "2",
        "title": "Customization Options",
        "category": "feature_request",
        "items": [
          {
            "type": "Constructive",
            "category": "Feature Request",
            "problemMetadata": {
              "rootCause": "Control",
              "featureArea": "Customization Options",
              "impactType": "Retention",
              "urgencySignal": "Low",
              "prioritization": {
                "impactScore": 6,
                "urgencyScore": 4,
                "effortEstimate": 2
              }
            },
            "delightMetadata": null,
            "summary": {
              "actionableInsight": "Prioritize expanding customization options for user interfaces and automation features.",
              "replyDraft": "Thanks for sharing your ideas! It sounds like a fun project to create a rewards system in Notion. While we currently have some customization options, we’re always looking to improve. Your feedback on adding more features is valuable, and we’ll keep it in mind for future updates!",
              "keyQuote": "I want to customize the color and other features. I want it all pinkkkkkkk!"
            },
            "confidence": 0.85,
            "reasoning": "The feedback clearly expresses a desire for new features related to customization and automation, indicating a need for more control over the user experience. The request for specific color customization and automation suggests a feature request rather than usability friction or support question.",
            "sourceUrl": "https://www.reddit.com/r/Notion/comments/1ub9dtf/i_need_ideas_for_habit_rewards_and_what_i_can/",
            "sourceId": "1ub9dtf",
            "originalTitle": "I need ideas for habit rewards and what I can customize?",
            "signalScore": 0.5999999999999999,
            "impactData": {
              "score": 2.1,
              "maxScore": 10,
              "breakdown": {
                "reach": {
                  "value": 0,
                  "weight": 0.4
                },
                "sentiment": {
                  "value": 7,
                  "weight": 0.3
                },
                "velocity": {
                  "value": 0,
                  "weight": 0.3
                }
              },
              "rationale": "Score based on standard engagement metrics.",
              "stakes": {
                "type": "risk",
                "message": "Risk if ignored: Continued user frustration, possible support ticket increase."
              }
            }
          }
        ],
        "totalScore": 2.1,
        "quotes": [
          "I want to customize the color and other features. I want it all pinkkkkkkk!"
        ],
        "segments": {},
        "frequency": 1,
        "avgImpact": 2.1,
        "topQuote": "I want to customize the color and other features. I want it all pinkkkkkkk!",
        "affectedSegments": [],
        "stakes": {
          "type": "risk",
          "message": "Risk if ignored: Continued user frustration, possible support ticket increase."
        },
        "scoreRationale": "Score based on standard engagement metrics.",
        "severityLabel": "Medium",
        "rootCause": "Lack of interface customization options.",
        "impactScore": 2.1,
        "trend": "new",
        "trendDelta": 0
      },
      {
        "id": "3",
        "title": "App Stability",
        "category": "usability_friction",
        "items": [
          {
            "type": "Constructive",
            "category": "Usability Friction",
            "problemMetadata": {
              "rootCause": "Reliability",
              "featureArea": "App Stability",
              "impactType": "Retention",
              "urgencySignal": "Critical",
              "prioritization": {
                "impactScore": 9,
                "urgencyScore": 10,
                "effortEstimate": 3
              }
            },
            "delightMetadata": null,
            "summary": {
              "actionableInsight": "Prioritize fixing the app stability issues related to the 'render process gone' error, especially after Windows updates.",
              "replyDraft": "Hi there! I'm really sorry to hear about the crashing issues you're experiencing with Notion. It sounds frustrating, especially after trying so many troubleshooting steps. We're actively working on improving app stability, and your feedback is invaluable. Thank you for your patience!",
              "keyQuote": "Notion keeps crashing giving 'render process gone' error."
            },
            "confidence": 0.95,
            "reasoning": "The feedback clearly indicates a usability issue with the app crashing, which is a significant problem affecting user experience and retention. The user's detailed troubleshooting steps suggest a serious reliability concern, especially after a Windows update.",
            "sourceUrl": "https://www.reddit.com/r/Notion/comments/1ub54vv/notion_keeps_crashing_giving_render_process_gone/",
            "sourceId": "1ub54vv",
            "originalTitle": "Notion keeps crashing giving \"render process gone\" errror",
            "signalScore": 0.5999999999999999,
            "impactData": {
              "score": 2.1,
              "maxScore": 10,
              "breakdown": {
                "reach": {
                  "value": 0,
                  "weight": 0.4
                },
                "sentiment": {
                  "value": 7,
                  "weight": 0.3
                },
                "velocity": {
                  "value": 0,
                  "weight": 0.3
                }
              },
              "rationale": "Score based on standard engagement metrics.",
              "stakes": {
                "type": "risk",
                "message": "Risk if ignored: Continued user frustration, possible support ticket increase."
              }
            }
          }
        ],
        "totalScore": 2.1,
        "quotes": [
          "Notion keeps crashing giving 'render process gone' error."
        ],
        "segments": {},
        "frequency": 1,
        "avgImpact": 2.1,
        "topQuote": "Notion keeps crashing giving 'render process gone' error.",
        "affectedSegments": [],
        "stakes": {
          "type": "risk",
          "message": "Risk if ignored: Continued user frustration, possible support ticket increase."
        },
        "scoreRationale": "Score based on standard engagement metrics.",
        "severityLabel": "High",
        "rootCause": "Underlying software stability issues.",
        "impactScore": 2.1,
        "trend": "new",
        "trendDelta": 0
      },
      {
        "id": "4",
        "title": "Calendar Management",
        "category": "usability_friction",
        "items": [
          {
            "type": "Constructive",
            "category": "Usability Friction",
            "problemMetadata": {
              "rootCause": "Ease",
              "featureArea": "Calendar Management",
              "impactType": "Retention",
              "urgencySignal": "Low",
              "prioritization": {
                "impactScore": 6,
                "urgencyScore": 4,
                "effortEstimate": 2
              }
            },
            "delightMetadata": null,
            "summary": {
              "actionableInsight": "Prioritize improving the calendar event color management feature to enhance user experience.",
              "replyDraft": "Hi there! Thanks for sharing your experience with the calendar event colors in Notion. I understand how frustrating it can be when things don't work as expected. While I can't provide a direct solution, I recommend checking our help center for tips or submitting a feature request for better color management. Your feedback is valuable!",
              "keyQuote": "It'd be really nice if there's a way to change its color!"
            },
            "confidence": 0.85,
            "reasoning": "The feedback clearly indicates a usability issue with the calendar event colors, where the user is experiencing frustration due to the lack of control over color settings. This aligns with the 'Usability Friction' category, and the root cause is identified as 'Ease' since the user seeks a simpler way to manage event colors.",
            "sourceUrl": "https://www.reddit.com/r/Notion/comments/1ub2mg7/how_to_change_the_color_of_a_calendar_event_from/",
            "sourceId": "1ub2mg7",
            "originalTitle": "How to change the color of a calendar event from my notion's database?",
            "signalScore": 0.5999999999999999,
            "impactData": {
              "score": 2.1,
              "maxScore": 10,
              "breakdown": {
                "reach": {
                  "value": 0,
                  "weight": 0.4
                },
                "sentiment": {
                  "value": 7,
                  "weight": 0.3
                },
                "velocity": {
                  "value": 0,
                  "weight": 0.3
                }
              },
              "rationale": "Score based on standard engagement metrics.",
              "stakes": {
                "type": "risk",
                "message": "Risk if ignored: Continued user frustration, possible support ticket increase."
              }
            }
          }
        ],
        "totalScore": 2.1,
        "quotes": [
          "It'd be really nice if there's a way to change its color!"
        ],
        "segments": {},
        "frequency": 1,
        "avgImpact": 2.1,
        "topQuote": "It'd be really nice if there's a way to change its color!",
        "affectedSegments": [],
        "stakes": {
          "type": "risk",
          "message": "Risk if ignored: Continued user frustration, possible support ticket increase."
        },
        "scoreRationale": "Score based on standard engagement metrics.",
        "severityLabel": "Medium",
        "rootCause": "Limited customization in calendar features.",
        "impactScore": 2.1,
        "trend": "new",
        "trendDelta": 0
      },
      {
        "id": "5",
        "title": "Pinned Properties",
        "category": "usability_friction",
        "items": [
          {
            "type": "Constructive",
            "category": "Usability Friction",
            "problemMetadata": {
              "rootCause": "Ease",
              "featureArea": "Pinned Properties",
              "impactType": "Retention",
              "urgencySignal": "High",
              "prioritization": {
                "impactScore": 7,
                "urgencyScore": 8,
                "effortEstimate": 2
              }
            },
            "delightMetadata": null,
            "summary": {
              "actionableInsight": "Prioritize improving the visual flexibility of pinned properties to enhance user experience.",
              "replyDraft": "Hi there! Thanks for sharing your thoughts. We understand how important the appearance of your workspace is, and we're sorry to hear that the recent changes have affected the look of your pinned properties. Your feedback is valuable, and we'll take it into consideration as we work on future updates!",
              "keyQuote": "...now everything seems to have a min width and I think it looks pretty dreadful."
            },
            "confidence": 0.85,
            "reasoning": "The feedback clearly expresses dissatisfaction with a recent change in the UI regarding pinned properties, indicating usability friction. The user struggles with the new default width, which affects the overall aesthetic and usability of their workspace.",
            "sourceUrl": "https://www.reddit.com/r/Notion/comments/1uavfz6/anyone_else_seeing_this_pinned_properties_now/",
            "sourceId": "1uavfz6",
            "originalTitle": "Anyone else seeing this? Pinned properties now have default width and it looks awful",
            "signalScore": 0.5999999999999999,
            "impactData": {
              "score": 2.1,
              "maxScore": 10,
              "breakdown": {
                "reach": {
                  "value": 0,
                  "weight": 0.4
                },
                "sentiment": {
                  "value": 7,
                  "weight": 0.3
                },
                "velocity": {
                  "value": 0,
                  "weight": 0.3
                }
              },
              "rationale": "Score based on standard engagement metrics.",
              "stakes": {
                "type": "risk",
                "message": "Risk if ignored: Continued user frustration, possible support ticket increase."
              }
            }
          }
        ],
        "totalScore": 2.1,
        "quotes": [
          "...now everything seems to have a min width and I think it looks pretty dreadful."
        ],
        "segments": {},
        "frequency": 1,
        "avgImpact": 2.1,
        "topQuote": "...now everything seems to have a min width and I think it looks pretty dreadful.",
        "affectedSegments": [],
        "stakes": {
          "type": "risk",
          "message": "Risk if ignored: Continued user frustration, possible support ticket increase."
        },
        "scoreRationale": "Score based on standard engagement metrics.",
        "severityLabel": "Medium",
        "rootCause": "Inflexible design constraints.",
        "impactScore": 2.1,
        "trend": "new",
        "trendDelta": 0
      },
      {
        "id": "6",
        "title": "Text Formatting Menu",
        "category": "usability_friction",
        "items": [
          {
            "type": "Constructive",
            "category": "Usability Friction",
            "problemMetadata": {
              "rootCause": "Ease",
              "featureArea": "Text Formatting Menu",
              "impactType": "Retention",
              "urgencySignal": "High",
              "prioritization": {
                "impactScore": 7,
                "urgencyScore": 8,
                "effortEstimate": 2
              }
            },
            "delightMetadata": null,
            "summary": {
              "actionableInsight": "Prioritize fixing the text formatting menu glitch to enhance user experience and retention.",
              "replyDraft": "Hi Jammyyy_jam, thanks for bringing this to our attention! We're sorry to hear about the glitch with the text formatting menu. Our team is looking into it, and we appreciate your patience as we work to improve the experience!",
              "keyQuote": "the menu when you selected some text showed up isnt showing up!"
            },
            "confidence": 0.85,
            "reasoning": "The feedback clearly indicates a usability issue with the text formatting menu, which affects user experience. The user expresses frustration with the alternative method, indicating a need for ease of use. The impact and urgency scores reflect the importance of addressing this issue promptly.",
            "sourceUrl": "https://www.reddit.com/r/Notion/comments/1uasym4/glitch_where_the_menu_when_you_selected_some_text/",
            "sourceId": "1uasym4",
            "originalTitle": "Glitch where the menu when you selected some text showed up isnt showing up! If i used ctrl + /, a similar menu comes up but its very bad to use!",
            "signalScore": 0.5999999999999999,
            "impactData": {
              "score": 2.1,
              "maxScore": 10,
              "breakdown": {
                "reach": {
                  "value": 0,
                  "weight": 0.4
                },
                "sentiment": {
                  "value": 7,
                  "weight": 0.3
                },
                "velocity": {
                  "value": 0,
                  "weight": 0.3
                }
              },
              "rationale": "Score based on standard engagement metrics.",
              "stakes": {
                "type": "risk",
                "message": "Risk if ignored: Continued user frustration, possible support ticket increase."
              }
            }
          }
        ],
        "totalScore": 2.1,
        "quotes": [
          "the menu when you selected some text showed up isnt showing up!"
        ],
        "segments": {},
        "frequency": 1,
        "avgImpact": 2.1,
        "topQuote": "the menu when you selected some text showed up isnt showing up!",
        "affectedSegments": [],
        "stakes": {
          "type": "risk",
          "message": "Risk if ignored: Continued user frustration, possible support ticket increase."
        },
        "scoreRationale": "Score based on standard engagement metrics.",
        "severityLabel": "High",
        "rootCause": "Bugs in text formatting interface.",
        "impactScore": 2.1,
        "trend": "new",
        "trendDelta": 0
      },
      {
        "id": "7",
        "title": "Notion Mail",
        "category": "usability_friction",
        "items": [
          {
            "type": "Constructive",
            "category": "Usability Friction",
            "problemMetadata": {
              "rootCause": "Speed",
              "featureArea": "Notion Mail",
              "impactType": "Retention",
              "urgencySignal": "Critical",
              "prioritization": {
                "impactScore": 9,
                "urgencyScore": 10,
                "effortEstimate": 3
              }
            },
            "delightMetadata": null,
            "summary": {
              "actionableInsight": "Prioritize performance optimization for Notion Mail to enhance user experience and retention.",
              "replyDraft": "Hey there! Thanks for sharing your thoughts on Notion Mail. We understand how frustrating slow loading times can be, and we appreciate your feedback. We're always looking to improve, and your insights will help us make Notion Mail better!",
              "keyQuote": "Notion Mail isn't an email client. It's a loading screen with commitment issues."
            },
            "confidence": 0.95,
            "reasoning": "The feedback clearly expresses frustration with the speed of Notion Mail, categorizing it as usability friction. The user highlights a specific area (Notion Mail) and indicates a strong emotional response, suggesting a critical need for improvement in speed to retain users.",
            "sourceUrl": "https://www.reddit.com/r/Notion/comments/1uaox4b/notion_mail_is_so_slow_it_makes_me_question_my/",
            "sourceId": "1uaox4b",
            "originalTitle": "Notion Mail is so slow it makes me question my life choices",
            "signalScore": 0.5999999999999999,
            "impactData": {
              "score": 2.1,
              "maxScore": 10,
              "breakdown": {
                "reach": {
                  "value": 0,
                  "weight": 0.4
                },
                "sentiment": {
                  "value": 7,
                  "weight": 0.3
                },
                "velocity": {
                  "value": 0,
                  "weight": 0.3
                }
              },
              "rationale": "Score based on standard engagement metrics.",
              "stakes": {
                "type": "risk",
                "message": "Risk if ignored: Continued user frustration, possible support ticket increase."
              }
            }
          },
          {
            "type": "Constructive",
            "category": "Usability Friction",
            "problemMetadata": {
              "rootCause": "Speed",
              "featureArea": "Notion Mail",
              "impactType": "Retention",
              "urgencySignal": "High",
              "prioritization": {
                "impactScore": 7,
                "urgencyScore": 8,
                "effortEstimate": 3
              }
            },
            "delightMetadata": null,
            "summary": {
              "actionableInsight": "Prioritize performance improvements and updates for Notion Mail to enhance user experience and retention.",
              "replyDraft": "Thank you for sharing your experience with Notion Mail! We appreciate your feedback and understand the importance of speed and updates. We're committed to improving the product and will take your insights into consideration as we plan future enhancements.",
              "keyQuote": "\"the product is very very slow and... it’s been in beta for a long time and seemingly has not been updated for many months.\""
            },
            "confidence": 0.85,
            "reasoning": "The feedback indicates a clear usability issue with Notion Mail, specifically regarding its speed and lack of updates, which aligns with the 'Usability Friction' category. The user expresses a desire for improvements, indicating a potential risk to retention if these issues are not addressed.",
            "sourceUrl": "https://www.reddit.com/r/Notion/comments/1u9hz5z/notion_mail/",
            "sourceId": "1u9hz5z",
            "originalTitle": "Notion Mail?",
            "signalScore": 0.5999999999999999,
            "impactData": {
              "score": 2.1,
              "maxScore": 10,
              "breakdown": {
                "reach": {
                  "value": 0,
                  "weight": 0.4
                },
                "sentiment": {
                  "value": 7,
                  "weight": 0.3
                },
                "velocity": {
                  "value": 0,
                  "weight": 0.3
                }
              },
              "rationale": "Score based on standard engagement metrics.",
              "stakes": {
                "type": "risk",
                "message": "Risk if ignored: Continued user frustration, possible support ticket increase."
              }
            }
          }
        ],
        "totalScore": 4.2,
        "quotes": [
          "Notion Mail isn't an email client. It's a loading screen with commitment issues.",
          "\"the product is very very slow and... it’s been in beta for a long time and seemingly has not been updated for many months.\""
        ],
        "segments": {},
        "frequency": 2,
        "avgImpact": 2.1,
        "topQuote": "Notion Mail isn't an email client. It's a loading screen with commitment issues.",
        "affectedSegments": [],
        "stakes": {
          "type": "risk",
          "message": "Risk if ignored: Continued user frustration, possible support ticket increase."
        },
        "scoreRationale": "Score based on standard engagement metrics.",
        "severityLabel": "High",
        "rootCause": "Performance and reliability issues with Notion Mail.",
        "impactScore": 2.1,
        "trend": "new",
        "trendDelta": 0
      },
      {
        "id": "8",
        "title": "Task Management",
        "category": "usability_friction",
        "items": [
          {
            "type": "Constructive",
            "category": "Support Question",
            "problemMetadata": {
              "rootCause": "Ease",
              "featureArea": "Task Management",
              "impactType": "Retention",
              "urgencySignal": "Low",
              "prioritization": {
                "impactScore": 6,
                "urgencyScore": 4,
                "effortEstimate": 2
              }
            },
            "delightMetadata": null,
            "summary": {
              "actionableInsight": "Investigate the possibility of creating a formula for date assignment in task management.",
              "replyDraft": "Hi there! It's great to see you back in Notion! While there isn't a built-in feature for assigning tasks to specific time frames like Day, Week, or Month, you can definitely create a formula to help with that. I recommend checking out the Notion community for some creative solutions, and feel free to share your progress!",
              "keyQuote": "I found this app called Bullet (.to) that has an option to assign tasks to a day, a week, a month, or even a year."
            },
            "confidence": 0.85,
            "reasoning": "The feedback clearly indicates a need for assistance in creating a specific task management system, which falls under the Support Question category. The user is looking for a formula, indicating a usability friction in the current task management capabilities.",
            "sourceUrl": "https://www.reddit.com/r/Notion/comments/1uahodj/assign_pages_to_day_week_or_month/",
            "sourceId": "1uahodj",
            "originalTitle": "Assign pages to Day, Week, or Month",
            "signalScore": 0.5999999999999999,
            "impactData": {
              "score": 2.1,
              "maxScore": 10,
              "breakdown": {
                "reach": {
                  "value": 0,
                  "weight": 0.4
                },
                "sentiment": {
                  "value": 7,
                  "weight": 0.3
                },
                "velocity": {
                  "value": 0,
                  "weight": 0.3
                }
              },
              "rationale": "Score based on standard engagement metrics.",
              "stakes": {
                "type": "risk",
                "message": "Risk if ignored: Continued user frustration, possible support ticket increase."
              }
            }
          },
          {
            "type": "Constructive",
            "category": "Usability Friction",
            "problemMetadata": {
              "rootCause": "Ease",
              "featureArea": "Task Management",
              "impactType": "Retention",
              "urgencySignal": "High",
              "prioritization": {
                "impactScore": 7,
                "urgencyScore": 8,
                "effortEstimate": 3
              }
            },
            "delightMetadata": null,
            "summary": {
              "actionableInsight": "Investigate simplifying the task management setup in Notion to enhance user retention and ease of use.",
              "replyDraft": "Thanks for sharing your experience! It sounds like you're really trying to make Notion work for you, and it's common to hit some bumps along the way. Many users find that starting with simpler setups can help maintain consistency. Have you considered exploring ways to streamline your workflow?",
              "keyQuote": "I slowly stop updating it and drift back to writing things on paper or using a simpler todo app."
            },
            "confidence": 0.85,
            "reasoning": "The feedback indicates a struggle with maintaining a complex setup in Notion, suggesting usability friction. The user expresses a need for simplicity and consistency, which aligns with the root cause of 'Ease'. The impact on retention is significant as users may abandon the tool if it feels too complicated.",
            "sourceUrl": "https://www.reddit.com/r/Notion/comments/1u98ext/how_are_you_actually_using_notion_for_task/",
            "sourceId": "1u98ext",
            "originalTitle": "How are you actually using Notion for task management day to day, does it stick?",
            "signalScore": 0.5999999999999999,
            "impactData": {
              "score": 2.1,
              "maxScore": 10,
              "breakdown": {
                "reach": {
                  "value": 0,
                  "weight": 0.4
                },
                "sentiment": {
                  "value": 7,
                  "weight": 0.3
                },
                "velocity": {
                  "value": 0,
                  "weight": 0.3
                }
              },
              "rationale": "Score based on standard engagement metrics.",
              "stakes": {
                "type": "risk",
                "message": "Risk if ignored: Continued user frustration, possible support ticket increase."
              }
            }
          }
        ],
        "totalScore": 4.2,
        "quotes": [
          "I found this app called Bullet (.to) that has an option to assign tasks to a day, a week, a month, or even a year.",
          "I slowly stop updating it and drift back to writing things on paper or using a simpler todo app."
        ],
        "segments": {},
        "frequency": 2,
        "avgImpact": 2.1,
        "topQuote": "I found this app called Bullet (.to) that has an option to assign tasks to a day, a week, a month, or even a year.",
        "affectedSegments": [],
        "stakes": {
          "type": "risk",
          "message": "Risk if ignored: Continued user frustration, possible support ticket increase."
        },
        "scoreRationale": "Score based on standard engagement metrics.",
        "severityLabel": "High",
        "rootCause": "Lack of advanced task management features.",
        "impactScore": 2.1,
        "trend": "new",
        "trendDelta": 0
      },
      {
        "id": "9",
        "title": "Content Management",
        "category": "usability_friction",
        "items": [
          {
            "type": "Constructive",
            "category": "Usability Friction",
            "problemMetadata": {
              "rootCause": "Ease",
              "featureArea": "Content Management",
              "impactType": "Retention",
              "urgencySignal": "High",
              "prioritization": {
                "impactScore": 8,
                "urgencyScore": 9,
                "effortEstimate": 3
              }
            },
            "delightMetadata": null,
            "summary": {
              "actionableInsight": "Prioritize simplifying the process of importing and organizing social media saves into Notion.",
              "replyDraft": "Thanks for sharing your experience! It sounds like managing saved content can be quite a challenge. We're always looking for ways to improve the user experience, and your insights on the importance of context are invaluable. Have you tried any specific features in Notion that help with this?",
              "keyQuote": "When I dump saves into Notion I get overwhelmed fast unless each entry has a short 'why I saved this' property."
            },
            "confidence": 0.85,
            "reasoning": "The feedback clearly identifies a usability issue with the current process of importing content into Notion, highlighting the need for simplification and better organization. The user expresses a struggle with overwhelming content management, indicating a need for improved usability.",
            "sourceUrl": "https://www.reddit.com/r/Notion/comments/1ua8qsu/anyone_else_have_a_graveyard_of_saved_posts_that/",
            "sourceId": "1ua8qsu",
            "originalTitle": "Anyone else have a graveyard of saved posts that never make it into Notion?",
            "signalScore": 0.5999999999999999,
            "impactData": {
              "score": 2.1,
              "maxScore": 10,
              "breakdown": {
                "reach": {
                  "value": 0,
                  "weight": 0.4
                },
                "sentiment": {
                  "value": 7,
                  "weight": 0.3
                },
                "velocity": {
                  "value": 0,
                  "weight": 0.3
                }
              },
              "rationale": "Score based on standard engagement metrics.",
              "stakes": {
                "type": "risk",
                "message": "Risk if ignored: Continued user frustration, possible support ticket increase."
              }
            }
          }
        ],
        "totalScore": 2.1,
        "quotes": [
          "When I dump saves into Notion I get overwhelmed fast unless each entry has a short 'why I saved this' property."
        ],
        "segments": {},
        "frequency": 1,
        "avgImpact": 2.1,
        "topQuote": "When I dump saves into Notion I get overwhelmed fast unless each entry has a short 'why I saved this' property.",
        "affectedSegments": [],
        "stakes": {
          "type": "risk",
          "message": "Risk if ignored: Continued user frustration, possible support ticket increase."
        },
        "scoreRationale": "Score based on standard engagement metrics.",
        "severityLabel": "Medium",
        "rootCause": "Overwhelming content management without clear organization tools.",
        "impactScore": 2.1,
        "trend": "new",
        "trendDelta": 0
      },
      {
        "id": "10",
        "title": "Integrations",
        "category": "usability_friction",
        "items": [
          {
            "type": "Constructive",
            "category": "Support Question",
            "problemMetadata": {
              "rootCause": "Ease",
              "featureArea": "Integrations",
              "impactType": "Cost to Serve",
              "urgencySignal": "High",
              "prioritization": {
                "impactScore": 7,
                "urgencyScore": 8,
                "effortEstimate": 3
              }
            },
            "delightMetadata": null,
            "summary": {
              "actionableInsight": "Investigate integration options for ticketing systems within Notion to streamline user requests and responses.",
              "replyDraft": "Hi there! It sounds like you're facing some challenges with managing your ticketing system in Notion. While we currently don't have a direct integration for email conversations, I recommend exploring third-party tools that can connect with Notion to simplify this process. If you have any specific tools in mind, feel free to share, and we can help brainstorm solutions!",
              "keyQuote": "We just don't know how to connect it all."
            },
            "confidence": 0.85,
            "reasoning": "The feedback clearly indicates a struggle with integrating email conversations into Notion, which falls under a support question. The user is seeking help and tips, indicating a need for ease in their workflow.",
            "sourceUrl": "https://www.reddit.com/r/Notion/comments/1ua48wr/ticketing_system/",
            "sourceId": "1ua48wr",
            "originalTitle": "Ticketing system",
            "signalScore": 0.5999999999999999,
            "impactData": {
              "score": 2.1,
              "maxScore": 10,
              "breakdown": {
                "reach": {
                  "value": 0,
                  "weight": 0.4
                },
                "sentiment": {
                  "value": 7,
                  "weight": 0.3
                },
                "velocity": {
                  "value": 0,
                  "weight": 0.3
                }
              },
              "rationale": "Score based on standard engagement metrics.",
              "stakes": {
                "type": "risk",
                "message": "Risk if ignored: Continued user frustration, possible support ticket increase."
              }
            }
          }
        ],
        "totalScore": 2.1,
        "quotes": [
          "We just don't know how to connect it all."
        ],
        "segments": {},
        "frequency": 1,
        "avgImpact": 2.1,
        "topQuote": "We just don't know how to connect it all.",
        "affectedSegments": [],
        "stakes": {
          "type": "risk",
          "message": "Risk if ignored: Continued user frustration, possible support ticket increase."
        },
        "scoreRationale": "Score based on standard engagement metrics.",
        "severityLabel": "Medium",
        "rootCause": "Insufficient integration capabilities with other tools.",
        "impactScore": 2.1,
        "trend": "new",
        "trendDelta": 0
      }
    ],
    "brandStrengths": {
      "overallScore": 6.5,
      "topLoves": [
        {
          "feature": "Flexibility",
          "quote": "I have a few different databases right now and want a master database to manage the items both in their separate databases as well as together.",
          "shareability": 8
        },
        {
          "feature": "Potential for Customization",
          "quote": "It'd be really nice if there's a way to change its color!",
          "shareability": 7
        },
        {
          "feature": "Comprehensive Features",
          "quote": "Anyone have a good reading tracker?",
          "shareability": 6
        }
      ],
      "brandPersonality": [
        "Innovative",
        "Versatile",
        "Complex"
      ]
    },
    "suggestedOKRs": [
      {
        "theme": "Improve Usability",
        "objective": "Enhance the stability and usability of core features.",
        "keyResults": [
          "Reduce app crash reports by 50% by end of Q2.",
          "Resolve 80% of reported text formatting bugs by Q2.",
          "Improve Notion Mail load times by 30% by Q2."
        ],
        "timeframe": "Q2"
      },
      {
        "theme": "Expand Customization",
        "objective": "Increase user interface customization options.",
        "keyResults": [
          "Implement color customization for key interface elements by Q3.",
          "Introduce customizable layout options by Q3.",
          "Gather user feedback on new customization features with 80% positive response by Q3."
        ],
        "timeframe": "Q3"
      },
      {
        "theme": "Enhance Integration Capabilities",
        "objective": "Improve integration with third-party tools.",
        "keyResults": [
          "Launch 3 new integrations with popular productivity tools by Q4.",
          "Increase user satisfaction with integrations by 20% by Q4.",
          "Conduct a user survey to identify top desired integrations by Q3."
        ],
        "timeframe": "Q4"
      }
    ],
    "priorityMatrix": [
      {
        "title": "AI Assistance",
        "category": "usability_friction",
        "impactScore": 2.1,
        "effortEstimate": "Quick Win",
        "quadrant": "Quick Wins",
        "frequency": 1
      },
      {
        "title": "Customization Options",
        "category": "feature_request",
        "impactScore": 2.1,
        "effortEstimate": "Medium",
        "quadrant": "Strategic Investments",
        "frequency": 1
      },
      {
        "title": "App Stability",
        "category": "usability_friction",
        "impactScore": 2.1,
        "effortEstimate": "Medium",
        "quadrant": "Strategic Investments",
        "frequency": 1
      },
      {
        "title": "Calendar Management",
        "category": "usability_friction",
        "impactScore": 2.1,
        "effortEstimate": "Quick Win",
        "quadrant": "Quick Wins",
        "frequency": 1
      },
      {
        "title": "Pinned Properties",
        "category": "usability_friction",
        "impactScore": 2.1,
        "effortEstimate": "Quick Win",
        "quadrant": "Quick Wins",
        "frequency": 1
      },
      {
        "title": "Text Formatting Menu",
        "category": "usability_friction",
        "impactScore": 2.1,
        "effortEstimate": "Medium",
        "quadrant": "Strategic Investments",
        "frequency": 1
      },
      {
        "title": "Notion Mail",
        "category": "usability_friction",
        "impactScore": 2.1,
        "effortEstimate": "Medium",
        "quadrant": "Strategic Investments",
        "frequency": 2
      },
      {
        "title": "Task Management",
        "category": "usability_friction",
        "impactScore": 2.1,
        "effortEstimate": "Medium",
        "quadrant": "Strategic Investments",
        "frequency": 2
      },
      {
        "title": "Content Management",
        "category": "usability_friction",
        "impactScore": 2.1,
        "effortEstimate": "Quick Win",
        "quadrant": "Quick Wins",
        "frequency": 1
      },
      {
        "title": "Integrations",
        "category": "usability_friction",
        "impactScore": 2.1,
        "effortEstimate": "Medium",
        "quadrant": "Strategic Investments",
        "frequency": 1
      }
    ],
    "expectationGaps": [
      {
        "expectation": "AI assistance should be unlimited and intuitive.",
        "reality": "Users are unclear about AI capabilities and limitations.",
        "gapSeverity": "Medium",
        "suggestedFix": "Provide clear documentation and tutorials on AI features."
      },
      {
        "expectation": "The app should be stable and reliable.",
        "reality": "Frequent crashes and errors reported.",
        "gapSeverity": "High",
        "suggestedFix": "Conduct a thorough review and optimization of app stability."
      },
      {
        "expectation": "Customization options should be extensive.",
        "reality": "Limited customization available, leading to user frustration.",
        "gapSeverity": "High",
        "suggestedFix": "Expand customization features to include color and layout options."
      }
    ],
    "metadata": {
      "totalAnalyzed": 50,
      "highSignalCount": 23,
      "noiseFiltered": 27,
      "dataSources": [
        "Reddit"
      ],
      "analysisDate": "2026-06-21T00:55:13.238Z"
    },
    "rawScores": [
      {
        "id": "1uban65",
        "impactData": {
          "score": 2.1,
          "maxScore": 10,
          "breakdown": {
            "reach": {
              "value": 0,
              "weight": 0.4
            },
            "sentiment": {
              "value": 7,
              "weight": 0.3
            },
            "velocity": {
              "value": 0,
              "weight": 0.3
            }
          },
          "rationale": "Score based on standard engagement metrics.",
          "stakes": {
            "type": "risk",
            "message": "Risk if ignored: Continued user frustration, possible support ticket increase."
          }
        }
      },
      {
        "id": "1ub9dtf",
        "impactData": {
          "score": 2.1,
          "maxScore": 10,
          "breakdown": {
            "reach": {
              "value": 0,
              "weight": 0.4
            },
            "sentiment": {
              "value": 7,
              "weight": 0.3
            },
            "velocity": {
              "value": 0,
              "weight": 0.3
            }
          },
          "rationale": "Score based on standard engagement metrics.",
          "stakes": {
            "type": "risk",
            "message": "Risk if ignored: Continued user frustration, possible support ticket increase."
          }
        }
      },
      {
        "id": "1ub54vv",
        "impactData": {
          "score": 2.1,
          "maxScore": 10,
          "breakdown": {
            "reach": {
              "value": 0,
              "weight": 0.4
            },
            "sentiment": {
              "value": 7,
              "weight": 0.3
            },
            "velocity": {
              "value": 0,
              "weight": 0.3
            }
          },
          "rationale": "Score based on standard engagement metrics.",
          "stakes": {
            "type": "risk",
            "message": "Risk if ignored: Continued user frustration, possible support ticket increase."
          }
        }
      },
      {
        "id": "1ub2mg7",
        "impactData": {
          "score": 2.1,
          "maxScore": 10,
          "breakdown": {
            "reach": {
              "value": 0,
              "weight": 0.4
            },
            "sentiment": {
              "value": 7,
              "weight": 0.3
            },
            "velocity": {
              "value": 0,
              "weight": 0.3
            }
          },
          "rationale": "Score based on standard engagement metrics.",
          "stakes": {
            "type": "risk",
            "message": "Risk if ignored: Continued user frustration, possible support ticket increase."
          }
        }
      },
      {
        "id": "1uavfz6",
        "impactData": {
          "score": 2.1,
          "maxScore": 10,
          "breakdown": {
            "reach": {
              "value": 0,
              "weight": 0.4
            },
            "sentiment": {
              "value": 7,
              "weight": 0.3
            },
            "velocity": {
              "value": 0,
              "weight": 0.3
            }
          },
          "rationale": "Score based on standard engagement metrics.",
          "stakes": {
            "type": "risk",
            "message": "Risk if ignored: Continued user frustration, possible support ticket increase."
          }
        }
      },
      {
        "id": "1uasym4",
        "impactData": {
          "score": 2.1,
          "maxScore": 10,
          "breakdown": {
            "reach": {
              "value": 0,
              "weight": 0.4
            },
            "sentiment": {
              "value": 7,
              "weight": 0.3
            },
            "velocity": {
              "value": 0,
              "weight": 0.3
            }
          },
          "rationale": "Score based on standard engagement metrics.",
          "stakes": {
            "type": "risk",
            "message": "Risk if ignored: Continued user frustration, possible support ticket increase."
          }
        }
      },
      {
        "id": "1uaox4b",
        "impactData": {
          "score": 2.1,
          "maxScore": 10,
          "breakdown": {
            "reach": {
              "value": 0,
              "weight": 0.4
            },
            "sentiment": {
              "value": 7,
              "weight": 0.3
            },
            "velocity": {
              "value": 0,
              "weight": 0.3
            }
          },
          "rationale": "Score based on standard engagement metrics.",
          "stakes": {
            "type": "risk",
            "message": "Risk if ignored: Continued user frustration, possible support ticket increase."
          }
        }
      },
      {
        "id": "1uahodj",
        "impactData": {
          "score": 2.1,
          "maxScore": 10,
          "breakdown": {
            "reach": {
              "value": 0,
              "weight": 0.4
            },
            "sentiment": {
              "value": 7,
              "weight": 0.3
            },
            "velocity": {
              "value": 0,
              "weight": 0.3
            }
          },
          "rationale": "Score based on standard engagement metrics.",
          "stakes": {
            "type": "risk",
            "message": "Risk if ignored: Continued user frustration, possible support ticket increase."
          }
        }
      },
      {
        "id": "1ua8qsu",
        "impactData": {
          "score": 2.1,
          "maxScore": 10,
          "breakdown": {
            "reach": {
              "value": 0,
              "weight": 0.4
            },
            "sentiment": {
              "value": 7,
              "weight": 0.3
            },
            "velocity": {
              "value": 0,
              "weight": 0.3
            }
          },
          "rationale": "Score based on standard engagement metrics.",
          "stakes": {
            "type": "risk",
            "message": "Risk if ignored: Continued user frustration, possible support ticket increase."
          }
        }
      },
      {
        "id": "1ua48wr",
        "impactData": {
          "score": 2.1,
          "maxScore": 10,
          "breakdown": {
            "reach": {
              "value": 0,
              "weight": 0.4
            },
            "sentiment": {
              "value": 7,
              "weight": 0.3
            },
            "velocity": {
              "value": 0,
              "weight": 0.3
            }
          },
          "rationale": "Score based on standard engagement metrics.",
          "stakes": {
            "type": "risk",
            "message": "Risk if ignored: Continued user frustration, possible support ticket increase."
          }
        }
      },
      {
        "id": "1ua1m1b",
        "impactData": {
          "score": 2.1,
          "maxScore": 10,
          "breakdown": {
            "reach": {
              "value": 0,
              "weight": 0.4
            },
            "sentiment": {
              "value": 7,
              "weight": 0.3
            },
            "velocity": {
              "value": 0,
              "weight": 0.3
            }
          },
          "rationale": "Score based on standard engagement metrics.",
          "stakes": {
            "type": "risk",
            "message": "Risk if ignored: Continued user frustration, possible support ticket increase."
          }
        }
      },
      {
        "id": "1u9yl55",
        "impactData": {
          "score": 2.1,
          "maxScore": 10,
          "breakdown": {
            "reach": {
              "value": 0,
              "weight": 0.4
            },
            "sentiment": {
              "value": 7,
              "weight": 0.3
            },
            "velocity": {
              "value": 0,
              "weight": 0.3
            }
          },
          "rationale": "Score based on standard engagement metrics.",
          "stakes": {
            "type": "risk",
            "message": "Risk if ignored: Continued user frustration, possible support ticket increase."
          }
        }
      },
      {
        "id": "1u9vfk3",
        "impactData": {
          "score": 2.1,
          "maxScore": 10,
          "breakdown": {
            "reach": {
              "value": 0,
              "weight": 0.4
            },
            "sentiment": {
              "value": 7,
              "weight": 0.3
            },
            "velocity": {
              "value": 0,
              "weight": 0.3
            }
          },
          "rationale": "Score based on standard engagement metrics.",
          "stakes": {
            "type": "risk",
            "message": "Risk if ignored: Continued user frustration, possible support ticket increase."
          }
        }
      },
      {
        "id": "1u9tc3k",
        "impactData": {
          "score": 2.1,
          "maxScore": 10,
          "breakdown": {
            "reach": {
              "value": 0,
              "weight": 0.4
            },
            "sentiment": {
              "value": 7,
              "weight": 0.3
            },
            "velocity": {
              "value": 0,
              "weight": 0.3
            }
          },
          "rationale": "Score based on standard engagement metrics.",
          "stakes": {
            "type": "risk",
            "message": "Risk if ignored: Continued user frustration, possible support ticket increase."
          }
        }
      },
      {
        "id": "1u9qtj7",
        "impactData": {
          "score": 2.1,
          "maxScore": 10,
          "breakdown": {
            "reach": {
              "value": 0,
              "weight": 0.4
            },
            "sentiment": {
              "value": 7,
              "weight": 0.3
            },
            "velocity": {
              "value": 0,
              "weight": 0.3
            }
          },
          "rationale": "Score based on standard engagement metrics.",
          "stakes": {
            "type": "risk",
            "message": "Risk if ignored: Continued user frustration, possible support ticket increase."
          }
        }
      },
      {
        "id": "1u9hz5z",
        "impactData": {
          "score": 2.1,
          "maxScore": 10,
          "breakdown": {
            "reach": {
              "value": 0,
              "weight": 0.4
            },
            "sentiment": {
              "value": 7,
              "weight": 0.3
            },
            "velocity": {
              "value": 0,
              "weight": 0.3
            }
          },
          "rationale": "Score based on standard engagement metrics.",
          "stakes": {
            "type": "risk",
            "message": "Risk if ignored: Continued user frustration, possible support ticket increase."
          }
        }
      },
      {
        "id": "1u9dv3f",
        "impactData": {
          "score": 2.1,
          "maxScore": 10,
          "breakdown": {
            "reach": {
              "value": 0,
              "weight": 0.4
            },
            "sentiment": {
              "value": 7,
              "weight": 0.3
            },
            "velocity": {
              "value": 0,
              "weight": 0.3
            }
          },
          "rationale": "Score based on standard engagement metrics.",
          "stakes": {
            "type": "risk",
            "message": "Risk if ignored: Continued user frustration, possible support ticket increase."
          }
        }
      },
      {
        "id": "1u9abqc",
        "impactData": {
          "score": 2.1,
          "maxScore": 10,
          "breakdown": {
            "reach": {
              "value": 0,
              "weight": 0.4
            },
            "sentiment": {
              "value": 7,
              "weight": 0.3
            },
            "velocity": {
              "value": 0,
              "weight": 0.3
            }
          },
          "rationale": "Score based on standard engagement metrics.",
          "stakes": {
            "type": "risk",
            "message": "Risk if ignored: Continued user frustration, possible support ticket increase."
          }
        }
      },
      {
        "id": "1u98ext",
        "impactData": {
          "score": 2.1,
          "maxScore": 10,
          "breakdown": {
            "reach": {
              "value": 0,
              "weight": 0.4
            },
            "sentiment": {
              "value": 7,
              "weight": 0.3
            },
            "velocity": {
              "value": 0,
              "weight": 0.3
            }
          },
          "rationale": "Score based on standard engagement metrics.",
          "stakes": {
            "type": "risk",
            "message": "Risk if ignored: Continued user frustration, possible support ticket increase."
          }
        }
      },
      {
        "id": "1u95oul",
        "impactData": {
          "score": 2.1,
          "maxScore": 10,
          "breakdown": {
            "reach": {
              "value": 0,
              "weight": 0.4
            },
            "sentiment": {
              "value": 7,
              "weight": 0.3
            },
            "velocity": {
              "value": 0,
              "weight": 0.3
            }
          },
          "rationale": "Score based on standard engagement metrics.",
          "stakes": {
            "type": "risk",
            "message": "Risk if ignored: Continued user frustration, possible support ticket increase."
          }
        }
      },
      {
        "id": "1u94ut4",
        "impactData": {
          "score": 2.1,
          "maxScore": 10,
          "breakdown": {
            "reach": {
              "value": 0,
              "weight": 0.4
            },
            "sentiment": {
              "value": 7,
              "weight": 0.3
            },
            "velocity": {
              "value": 0,
              "weight": 0.3
            }
          },
          "rationale": "Score based on standard engagement metrics.",
          "stakes": {
            "type": "risk",
            "message": "Risk if ignored: Continued user frustration, possible support ticket increase."
          }
        }
      },
      {
        "id": "1u938wh",
        "impactData": {
          "score": 2.1,
          "maxScore": 10,
          "breakdown": {
            "reach": {
              "value": 0,
              "weight": 0.4
            },
            "sentiment": {
              "value": 7,
              "weight": 0.3
            },
            "velocity": {
              "value": 0,
              "weight": 0.3
            }
          },
          "rationale": "Score based on standard engagement metrics.",
          "stakes": {
            "type": "risk",
            "message": "Risk if ignored: Continued user frustration, possible support ticket increase."
          }
        }
      },
      {
        "id": "1u92yrs",
        "impactData": {
          "score": 2.1,
          "maxScore": 10,
          "breakdown": {
            "reach": {
              "value": 0,
              "weight": 0.4
            },
            "sentiment": {
              "value": 7,
              "weight": 0.3
            },
            "velocity": {
              "value": 0,
              "weight": 0.3
            }
          },
          "rationale": "Score based on standard engagement metrics.",
          "stakes": {
            "type": "risk",
            "message": "Risk if ignored: Continued user frustration, possible support ticket increase."
          }
        }
      }
    ]
  },
  "metadata": {
    "totalAnalyzed": 50,
    "dataSources": [
      "reddit"
    ],
    "subredditsSearched": [],
    "created_by": "terminal_scout",
    "version": "2.0"
  },
  "lastUpdated": "2026-06-21T00:55:13.238Z"
}